[
  {
    "ParameterKey": "Env",
    "ParameterValue": "dev"
  },
  {
    "ParameterKey": "WorkloadName",
    "ParameterValue": "vcis-app-sam-sample-app-two"
  },
  {
    "ParameterKey": "S3SourceKey",
    "ParameterValue": "vcis-sam-sample-app-two-dev"
  },
  {
    "ParameterKey": "AppAccountLevelResourcesStackName",
    "ParameterValue": "vcis-app-non-prod-account-level-resources"
  },
  {
    "ParameterKey": "ApprovalNotificationsStackName",
    "ParameterValue": ""
  },
  {
    "ParameterKey": "ProjectModuleTag",
    "ParameterValue": "/vcis/dev/infra/tags/project-module-pod"
  }
]
